xrally_kubernetes/__init__.py
xrally_kubernetes/service.py
xrally_kubernetes/common/__init__.py
xrally_kubernetes/common/opts.py
xrally_kubernetes/env/__init__.py
xrally_kubernetes/env/platforms/__init__.py
xrally_kubernetes/env/platforms/existing.py
xrally_kubernetes/tasks/__init__.py
xrally_kubernetes/tasks/context.py
xrally_kubernetes/tasks/scenario.py
xrally_kubernetes/tasks/validators.py
xrally_kubernetes/tasks/contexts/__init__.py
xrally_kubernetes/tasks/contexts/local_storageclass.py
xrally_kubernetes/tasks/contexts/namespaces.py
xrally_kubernetes/tasks/scenarios/__init__.py
xrally_kubernetes/tasks/scenarios/daemonsets.py
xrally_kubernetes/tasks/scenarios/deployments.py
xrally_kubernetes/tasks/scenarios/jobs.py
xrally_kubernetes/tasks/scenarios/namespaces.py
xrally_kubernetes/tasks/scenarios/pods.py
xrally_kubernetes/tasks/scenarios/replicasets.py
xrally_kubernetes/tasks/scenarios/replication_controllers.py
xrally_kubernetes/tasks/scenarios/services.py
xrally_kubernetes/tasks/scenarios/statefulsets.py
xrally_kubernetes/tasks/scenarios/volumes/__init__.py
xrally_kubernetes/tasks/scenarios/volumes/base.py
xrally_kubernetes/tasks/scenarios/volumes/configmap.py
xrally_kubernetes/tasks/scenarios/volumes/emptydir.py
xrally_kubernetes/tasks/scenarios/volumes/hostpath.py
xrally_kubernetes/tasks/scenarios/volumes/local_persistent_volume.py
xrally_kubernetes/tasks/scenarios/volumes/secret.py
xrally_kubernetes/verify/__init__.py
xrally_kubernetes-1.1.1.dist-info/DESCRIPTION.rst
xrally_kubernetes-1.1.1.dist-info/METADATA
xrally_kubernetes-1.1.1.dist-info/RECORD
xrally_kubernetes-1.1.1.dist-info/WHEEL
xrally_kubernetes-1.1.1.dist-info/entry_points.txt
xrally_kubernetes-1.1.1.dist-info/metadata.json
xrally_kubernetes-1.1.1.dist-info/pbr.json
xrally_kubernetes-1.1.1.dist-info/top_level.txt
