Metadata-Version: 2.0
Name: xrally-kubernetes
Version: 1.1.1
Summary: A set of xRally plugins to run workloads against Kubernetes platform.
Home-page: https://xrally.org/plugins/kubernetes/overview
Author: xRally Team
License: Apache License, Version 2.0
Platform: UNKNOWN
Classifier: Intended Audience :: Developers
Classifier: Intended Audience :: Information Technology
Classifier: License :: OSI Approved :: Apache Software License
Classifier: Operating System :: POSIX :: Linux
Classifier: Programming Language :: Python
Classifier: Programming Language :: Python :: 2
Classifier: Programming Language :: Python :: 2.7
Classifier: Programming Language :: Python :: 3
Classifier: Programming Language :: Python :: 3.4
Classifier: Programming Language :: Python :: 3.5
Classifier: Programming Language :: Python :: 3.6
Requires-Dist: kubernetes (>=5.0.0)
Requires-Dist: rally (>=1.2.0)
Requires-Dist: requests
Requires-Dist: setuptools-scm
